Henson_AMQP-0.9.0.dist-info/DESCRIPTION.rst
Henson_AMQP-0.9.0.dist-info/METADATA
Henson_AMQP-0.9.0.dist-info/RECORD
Henson_AMQP-0.9.0.dist-info/WHEEL
Henson_AMQP-0.9.0.dist-info/metadata.json
Henson_AMQP-0.9.0.dist-info/top_level.txt
henson_amqp/__init__.py
