Metadata-Version: 2.0
Name: Henson-AMQP
Version: 0.9.0
Summary: A library for interacting with AMQP with a Henson application.
Home-page: https://henson-amqp.readthedocs.io
Author: Leonard Bedner, Christian Paul, and others
Author-email: henson@iheart.com
License: Apache License, Version 2.0
Platform: UNKNOWN
Classifier: Development Status :: 4 - Beta
Classifier: Intended Audience :: Developers
Classifier: License :: OSI Approved :: Apache Software License
Classifier: Natural Language :: English
Classifier: Operating System :: POSIX
Classifier: Programming Language :: Python
Classifier: Programming Language :: Python :: 3.8
Classifier: Programming Language :: Python :: 3.9
Classifier: Programming Language :: Python :: 3 :: Only
Classifier: Topic :: Software Development :: Libraries :: Application Frameworks
Requires-Dist: Henson (<3.0.0,>=1.0.0)
Requires-Dist: aioamqp (<1.0.0,>=0.5.1)
